exul/__init__.py
exul/__main__.py
exul/decorators.py
exul/enumerate.py
exul/utilities.py
exul/window.py
exul-0.0.4.dist-info/LICENSE
exul-0.0.4.dist-info/METADATA
exul-0.0.4.dist-info/WHEEL
exul-0.0.4.dist-info/top_level.txt
exul-0.0.4.dist-info/RECORD
