Metadata-Version: 2.1
Name: exul
Version: 0.0.4
Summary: A package for handling Xlib operations in an easy-to-use fashion.
Home-page: http://github.com/IanWernecke/exul
Author: IanWernecke
Author-email: IanWernecke@protonmail.com
License: GPLv3
Keywords: xlib xwindows x-windows mouse keyboard event events
Platform: UNKNOWN
Requires-Dist: Pillow
Requires-Dist: Xlib
Requires-Dist: herja (>=0.0.2)
